{"stat.useItem.minecraft.golden_apple":37,"stat.flyOneCm":98,"stat.walkOneCm":10111,"stat.drop":6,"stat.useItem.minecraft.sand":30,"stat.jump":18,"stat.mineBlock.minecraft.sand":1,"stat.playOneMinute":4392,"achievement.openInventory":3,"stat.fallOneCm":546,"stat.leaveGame":1,"stat.damageTaken":1070,"stat.damageDealt":10,"stat.timeSinceDeath":4392,"stat.useItem.minecraft.dirt":1,"stat.mineBlock.minecraft.dirt":1,"achievement.exploreAllBiomes":{"value":0,"progress":["Taiga"]},"stat.useItem.minecraft.cactus":14}